{"71b020fd-5e95-e811-80f8-005056ba18b6":{"AddressId":"d5c52432-5e95-e811-80f8-005056ba18b6","AddressName":"г. Москва, НАО, поселение Московский, д. Картмазово, уч. 16\/1, корпус 2 (нежилые)","Advantages":[],"ArticleId":"71b020fd-5e95-e811-80f8-005056ba18b6","ArticleSubType":"нежилое помещение","ArticleType":"Нежилое","BeforeBtiNumber":"3","BeforeBtiNumberTxt":"3","BtiNumber":[],"BtiNumberTxt":"3п","BuildingGroup":"ЖК «Филатов Луг»","BuildingGroupId":"54a82767-85da-e711-80e8-005056ba18b6","BuildingProjects":[],"BuildingProjectsSelected":[],"Category":"0","CeilingHeight":"6","Code":"ФЛ2н-01-01-03-003","Cost":"257213.0000","CountBalcony":"0","CountLoggia":"0","CountTerrace":"0","CreditProgramms":[],"DependentId":[],"DisableBronPersAcc":"false","DiscountDateEnd":[],"DiscountMax":"20937138.2000","FinishTypeId":"Без отделки","FirePlace":[],"Floor":"1","LayoutUrl":"https:\/\/portal.ingrad.com\/crm\/tisa_address\/Москва, д Картмазово, уч 16 1, корпус 2 (нежилые)\/Планировки\/ФЛ2н (3).jpg","Lead":"нежилое помещение|","LeadDateEnd":[],"LeadId":[],"MebelType":[],"ParkingType":[],"PentHouse":[],"PlatformNumber":"3","Price":"20937138.2000","Quantity":"81.4","Rooms":"0","RoomsBti":"Номер по плану 1 Офис, площадью 71,8 кв.м., Номер по плану 2 С\/У МГН, площадью 5,3 кв.м., Номер по плану 3 Санузел женский, площадью 2,2 кв.м., Номер по плану 4 Санузел мужской, площадью 2,1 кв.м.","RoomsProject":{"Room":[{"AreaProject":"71.9700000000","ArticleId":"71b020fd-5e95-e811-80f8-005056ba18b6","Name":"ФЛ2н-01-01-03-003 Офис","RoomNumber":[],"TypeName":"Офис"},{"AreaProject":"2.0500000000","ArticleId":"71b020fd-5e95-e811-80f8-005056ba18b6","Name":"ФЛ2н-01-01-03-003 С\/у женский","RoomNumber":[],"TypeName":"С\/у женский"},{"AreaProject":"2.0900000000","ArticleId":"71b020fd-5e95-e811-80f8-005056ba18b6","Name":"ФЛ2н-01-01-03-003 С\/у мужской","RoomNumber":[],"TypeName":"С\/у мужской"},{"AreaProject":"5.3600000000","ArticleId":"71b020fd-5e95-e811-80f8-005056ba18b6","Name":"ФЛ2н-01-01-03-003 С\/у для МГН","RoomNumber":[],"TypeName":"С\/У МГН"}]},"Sauna":"false","SectionId":"e1779842-5e95-e811-80f8-005056ba18b6","SectionName":"ФЛ2н-01","SectionNumber":"1","SeparateEntrance":[],"SmartHouseCategory":[],"SpaceBti":"81.4","SpaceDesign":"81.47","SpaceKitchen":[],"SpaceOut":[],"StatusCode":"4","StatusCodeName":"Свободно","Supply":"Поставка_ПДКП_10_000_не_входит","Terrace":"False","TownHouse":[],"TwoLevel":[],"TypeDescription":[],"UnitCode":"кв.м.","Vendor":"Бизнес Групп","WithWindow":[]}}